django_extra_validators/__init__.py
django_extra_validators/validators/__init__.py
django_extra_validators/validators/dutch_postal_code.py
django_extra_validators/validators/email.py
django_extra_validators/validators/iban.py
django_extra_validators/validators/url.py
django_extra_validators-0.1.2.dist-info/METADATA
django_extra_validators-0.1.2.dist-info/WHEEL
django_extra_validators-0.1.2.dist-info/RECORD
