Metadata-Version: 2.3
Name: django-extra-validators
Version: 0.1.2
Summary: Reusable Django validators (e.g. Dutch postal code, IBAN number, emoji filter, etc.)
Author: Rick Verbon
Author-email: rick89@gmail.com
Requires-Python: >=3.11
Classifier: Programming Language :: Python :: 3
Classifier: Programming Language :: Python :: 3.11
Classifier: Programming Language :: Python :: 3.12
Classifier: Programming Language :: Python :: 3.13
Requires-Dist: django (>=4.2,<5.2.1)
Requires-Dist: dnspython (>=2.7.0,<3.0.0)
Requires-Dist: pytest (>=8.3.5,<9.0.0)
Requires-Dist: requests (>=2.32.3,<3.0.0)
Requires-Dist: schwifty (>=2025.1.0,<2026.0.0)
